django_reactive/__init__.py
django_reactive/apps.py
django_reactive/fields.py
django_reactive/forms.py
django_reactive/static/css/django_reactive.css
django_reactive/static/dist/react-dom.js
django_reactive/static/dist/react-jsonschema-form.js
django_reactive/static/dist/react-jsonschema-form.js.map
django_reactive/static/dist/react.js
django_reactive/static/js/django_reactive.js
django_reactive/templates/django_reactive.html
django_reactive/widget/__init__.py
django_reactive/widget/fields.py
django_reactive/widget/widgets.py
django_reactive-0.0.12.dist-info/METADATA
django_reactive-0.0.12.dist-info/LICENSE
django_reactive-0.0.12.dist-info/WHEEL
django_reactive-0.0.12.dist-info/RECORD
