Metadata-Version: 2.1
Name: django-reactive
Version: 0.0.12
Summary: Django JSON form field on steroids
Home-page: https://github.com/tyomo4ka/django-reactive
License: MIT
Keywords: django,postgres,json,jsonschema,react
Author: Artem Kolesnikov
Author-email: tyomo4ka@gmail.com
Requires-Python: >=3.8.1,<4
Classifier: License :: OSI Approved :: MIT License
Classifier: Programming Language :: Python :: 3
Classifier: Programming Language :: Python :: 3.9
Classifier: Programming Language :: Python :: 3.10
Classifier: Programming Language :: Python :: 3.11
Requires-Dist: django (>=3.2,<5.0)
Requires-Dist: jsonschema (>=3.0,<5.0)
Requires-Dist: psycopg2-binary (>=2.7,<4.0)
Project-URL: Documentation, https://github.com/tyomo4ka/django-reactive
Project-URL: Repository, https://github.com/tyomo4ka/django-reactive
